anbimapy/__init__.py
anbimapy/anbima.py
anbimapy/auth.py
anbimapy/py.typed
anbimapy/apis/cri_cra.py
anbimapy/apis/debentures.py
anbimapy/apis/fidc.py
anbimapy/apis/ida_liq.py
anbimapy/apis/indice_mais.py
anbimapy/apis/indices.py
anbimapy/apis/letras_financeiras.py
anbimapy/apis/reune.py
anbimapy/apis/titulos_publicos.py
anbimapy-0.2.0.dist-info/METADATA
anbimapy-0.2.0.dist-info/WHEEL
anbimapy-0.2.0.dist-info/RECORD
