Metadata-Version: 2.4
Name: anbimapy
Version: 0.2.0
Summary: Add your description here
Author: Lucas Rodrigues
Requires-Python: >=3.9
Requires-Dist: httpx>=0.22
Requires-Dist: typing-extensions>=4.13.2
